{
    "Current Courses": [
        "PHYS1103",
        "CSE2023",
        "CSE2225",
        "ECON2004",
        "MATH2055",
        "MATH2059"
    ],
    "Execution Trace": [
        "Current Semester Courses: ",
        "PHYS1103, CSE2023, CSE2225, ECON2004, EE2031, MATH2055, MATH2059, ",
        "(0 NTE), (0 TE), (0 FTE), ",
        "",
        "The system didn't allow EE2031 because course section is full. (100)",
        "",
        "Current Courses: ",
        "PHYS1103, CSE2023, CSE2225, ECON2004, MATH2055, MATH2059, "
    ],
    "AdvisorName": "GÖKHAN ALMACIOĞLU",
    "SemesterNumber": 3,
    "Past Courses": [
        {
            "intGrade": 70,
            "LetterGrade": "CC",
            "Course": "ATA121"
        },
        {
            "intGrade": 72,
            "LetterGrade": "CC",
            "Course": "MBG1201"
        },
        {
            "intGrade": 73,
            "LetterGrade": "CC",
            "Course": "CSE1200"
        },
        {
            "intGrade": 83,
            "LetterGrade": "BB",
            "Course": "CSE1241"
        },
        {
            "intGrade": 59,
            "LetterGrade": "DC",
            "Course": "MATH1001"
        },
        {
            "intGrade": 74,
            "LetterGrade": "CC",
            "Course": "PHYS1101"
        },
        {
            "intGrade": 23,
            "LetterGrade": "FF",
            "Course": "PHYS1103"
        },
        {
            "intGrade": 55,
            "LetterGrade": "DC",
            "Course": "TRD121"
        },
        {
            "intGrade": 97,
            "LetterGrade": "AA",
            "Course": "ATA122"
        },
        {
            "intGrade": 77,
            "LetterGrade": "CB",
            "Course": "CSE1242"
        },
        {
            "intGrade": 87,
            "LetterGrade": "BA",
            "Course": "MATH1002"
        },
        {
            "intGrade": 68,
            "LetterGrade": "CC",
            "Course": "MATH2256"
        },
        {
            "intGrade": 82,
            "LetterGrade": "BB",
            "Course": "PHYS1102"
        },
        {
            "intGrade": 93,
            "LetterGrade": "AA",
            "Course": "PHYS1104"
        },
        {
            "intGrade": 8,
            "LetterGrade": "FF",
            "Course": "TRD122"
        },
        {
            "intGrade": 83,
            "LetterGrade": "BB",
            "Course": "YDF1002"
        }
    ],
    "StudentName": "MUSTAFA KABA",
    "CompletedCredits": 57,
    "StudentId": "150120059"
}