{
    "Current Courses": [
        "EE2031",
        "MATH2059",
        "CSE3033",
        "CSE3055",
        "ISG121",
        "CSE4288",
        "YDA1003",
        "CSE4061"
    ],
    "Execution Trace": [
        "Current Semester Courses: ",
        "EE2031, MATH2059, CSE3033, CSE3055, CSE4074, CSE4219, ISG121, CSE4288, CSE4297(Final Project), ",
        "(1 NTE), (1 TE), (0 FTE), ",
        "",
        "Advisor didn't approve CSE4074 because of more than one hour collision with -> CSE3033 CSE3033  in schedule",
        "The system didn't allow CSE4219 because student failed prerequisites -> CSE3038 ",
        "The system didn't allow CSE4297(Final Project) because Student completed credits is less than 165-> (155)",
        "",
        "Current Courses: ",
        "EE2031, MATH2059, CSE3033, CSE3055, ISG121, CSE4288, YDA1003(NTE/UE), CSE4061(TE), "
    ],
    "AdvisorName": "MUSTAFA ULAŞ GİRAY",
    "SemesterNumber": 7,
    "Past Courses": [
        {
            "intGrade": 52,
            "LetterGrade": "DD",
            "Course": "ATA121"
        },
        {
            "intGrade": 81,
            "LetterGrade": "BB",
            "Course": "MBG1201"
        },
        {
            "intGrade": 52,
            "LetterGrade": "DD",
            "Course": "CSE1200"
        },
        {
            "intGrade": 64,
            "LetterGrade": "DC",
            "Course": "CSE1241"
        },
        {
            "intGrade": 45,
            "LetterGrade": "FD",
            "Course": "MATH1001"
        },
        {
            "intGrade": 80,
            "LetterGrade": "BB",
            "Course": "PHYS1101"
        },
        {
            "intGrade": 82,
            "LetterGrade": "BB",
            "Course": "PHYS1103"
        },
        {
            "intGrade": 79,
            "LetterGrade": "CB",
            "Course": "TRD121"
        },
        {
            "intGrade": 81,
            "LetterGrade": "BB",
            "Course": "ATA122"
        },
        {
            "intGrade": 73,
            "LetterGrade": "CC",
            "Course": "CSE1242"
        },
        {
            "intGrade": 92,
            "LetterGrade": "AA",
            "Course": "MATH1002"
        },
        {
            "intGrade": 92,
            "LetterGrade": "AA",
            "Course": "MATH2256"
        },
        {
            "intGrade": 41,
            "LetterGrade": "FF",
            "Course": "PHYS1102"
        },
        {
            "intGrade": 70,
            "LetterGrade": "CC",
            "Course": "PHYS1104"
        },
        {
            "intGrade": 67,
            "LetterGrade": "CC",
            "Course": "TRD122"
        },
        {
            "intGrade": 70,
            "LetterGrade": "CC",
            "Course": "CSE2023"
        },
        {
            "intGrade": 43,
            "LetterGrade": "FF",
            "Course": "CSE2225"
        },
        {
            "intGrade": 81,
            "LetterGrade": "BB",
            "Course": "ECON2004"
        },
        {
            "intGrade": 71,
            "LetterGrade": "CC",
            "Course": "MATH2055"
        },
        {
            "intGrade": 75,
            "LetterGrade": "CB",
            "Course": "CSE2246"
        },
        {
            "intGrade": 13,
            "LetterGrade": "FF",
            "Course": "CSE2138"
        },
        {
            "intGrade": 55,
            "LetterGrade": "DC",
            "Course": "CSE2260"
        },
        {
            "intGrade": 92,
            "LetterGrade": "AA",
            "Course": "STAT2253"
        },
        {
            "intGrade": 72,
            "LetterGrade": "CC",
            "Course": "CSE3000"
        },
        {
            "intGrade": 97,
            "LetterGrade": "AA",
            "Course": "SOC3082"
        },
        {
            "intGrade": 59,
            "LetterGrade": "DC",
            "Course": "MATH1001"
        },
        {
            "intGrade": 81,
            "LetterGrade": "BB",
            "Course": "CSE2225"
        },
        {
            "intGrade": 69,
            "LetterGrade": "CC",
            "Course": "CSE3215"
        },
        {
            "intGrade": 80,
            "LetterGrade": "BB",
            "Course": "CSE3063"
        },
        {
            "intGrade": 90,
            "LetterGrade": "AA",
            "Course": "IE3081"
        },
        {
            "intGrade": 52,
            "LetterGrade": "DD",
            "Course": "PHYS1102"
        },
        {
            "intGrade": 70,
            "LetterGrade": "CC",
            "Course": "CSE2138"
        },
        {
            "intGrade": 89,
            "LetterGrade": "BA",
            "Course": "CSE3048"
        },
        {
            "intGrade": 79,
            "LetterGrade": "CB",
            "Course": "CSE3264"
        },
        {
            "intGrade": 93,
            "LetterGrade": "AA",
            "Course": "IE3235"
        },
        {
            "intGrade": 90,
            "LetterGrade": "AA",
            "Course": "COM2202"
        },
        {
            "intGrade": 65,
            "LetterGrade": "CC",
            "Course": "CSE4000"
        }
    ],
    "StudentName": "SERHAT TAŞAR",
    "CompletedCredits": 155,
    "StudentId": "150118040"
}